pyacme/ACMEobj.py
pyacme/__init__.py
pyacme/__main__.py
pyacme/actions.py
pyacme/base.py
pyacme/exceptions.py
pyacme/execution.py
pyacme/jwk.py
pyacme/jws.py
pyacme/request.py
pyacme/settings.py
pyacme/util.py
pyacme/dnsprovider/__init__.py
pyacme/dnsprovider/aliyun.py
pyacme/dnsprovider/dispatch.py
pyacme/dnsprovider/dnsproviderbase.py
pyacme-0.0.1rc0.dist-info/LICENSE
pyacme-0.0.1rc0.dist-info/METADATA
pyacme-0.0.1rc0.dist-info/WHEEL
pyacme-0.0.1rc0.dist-info/entry_points.txt
pyacme-0.0.1rc0.dist-info/top_level.txt
pyacme-0.0.1rc0.dist-info/RECORD
