Metadata-Version: 2.1
Name: pyacme
Version: 0.0.1rc0
Summary: A simple acme client written in python
Home-page: https://github.com/Juniormin123/pyacme
Author: Juniormin123
Author-email: min641366609@live.com
License: MIT
Keywords: ACME,certificate,letsencrypt
Platform: UNKNOWN
Classifier: License :: OSI Approved :: MIT License
Classifier: Development Status :: 2 - Pre-Alpha
Classifier: Programming Language :: Python :: 3 :: Only
Classifier: Programming Language :: Python :: 3.8
Classifier: Operating System :: POSIX :: Linux
Classifier: Environment :: Console
Requires-Python: >=3.6
Requires-Dist: requests
Requires-Dist: cryptography (>=3.2.1)
Requires-Dist: aliyun-python-sdk-core
Requires-Dist: aliyun-python-sdk-alidns
